dbm_database_service/__init__.py
dbm_database_service/connectors.py
dbm_database_service/managers.py
dbm_database_service/models/__init__.py
dbm_database_service/models/column.py
dbm_database_service/models/config.py
dbm_database_service/models/datatype.py
dbm_database_service/models/table.py
dbm_database_service-0.2.5.dist-info/METADATA
dbm_database_service-0.2.5.dist-info/WHEEL
dbm_database_service-0.2.5.dist-info/RECORD
