Metadata-Version: 2.1
Name: dbm-database-service
Version: 0.2.5
Summary: 
Author: Smolke
Author-email: d.smolczynski1@gmail.com
Requires-Python: >=3.11,<4.0
Classifier: Programming Language :: Python :: 3
Classifier: Programming Language :: Python :: 3.11
Requires-Dist: easyvalid-data-validator (>=2.0.1,<3.0.0)
Requires-Dist: gdown (>=4.7.1,<5.0.0)
Requires-Dist: mysql-connector-python (>=8.0.32,<9.0.0)
Requires-Dist: pytest (>=7.3.0,<8.0.0)
Requires-Dist: python-dotenv (>=1.0.0,<2.0.0)
